amethyst/__init__.py
amethyst/__main__.py
amethyst/amethyst.py
amethyst/commands_main.py
amethyst/io.py
amethyst/substitution.py
amethyst/utils.py
amethyst_rdkit-1.1.dist-info/LICENSE.MD
amethyst_rdkit-1.1.dist-info/METADATA
amethyst_rdkit-1.1.dist-info/WHEEL
amethyst_rdkit-1.1.dist-info/RECORD
